<?xml version="1.0" encoding="ISO-8859-1" ?>
<!DOCTYPE tiles-definitions PUBLIC
       "-//Apache Software Foundation//DTD Tiles Configuration 3.0//EN"
       "http://tiles.apache.org/dtds/tiles-config_3_0.dtd">
       
<tiles-definitions>
	<definition name="parking.base" template="/WEB-INF/templates/default.jsp">
		<put-attribute name="includes" value=""></put-attribute>
		<put-attribute name="title" value="Parking Homepage"></put-attribute>
		<put-attribute name="header" value="/WEB-INF/tiles/header.jsp"></put-attribute>
		<put-attribute name="content" value="/WEB-INF/tiles/content.jsp"></put-attribute>
		<put-attribute name="footer" value="/WEB-INF/tiles/footer.jsp"></put-attribute>
	</definition>
	
	<definition name="home" extends="parking.base">
		<put-attribute name="title" value="Parking Homepage"></put-attribute>
		<put-attribute name="content" value="/WEB-INF/tiles/home.jsp"></put-attribute>
	</definition>
	
	<definition name="login" extends="parking.base">
		<put-attribute name="title" value="Login"></put-attribute>
		<put-attribute name="content" value="/WEB-INF/tiles/account/login.jsp"></put-attribute>
	</definition>
	
	<definition name="loggedout" extends="parking.base">
		<put-attribute name="title" value="Loggedout Page"></put-attribute>
		<put-attribute name="content" value="/WEB-INF/tiles/account/loggedout.jsp"></put-attribute>
	</definition>
	
	<definition name="newaccount" extends="parking.base">
		<put-attribute name="includes" value="/WEB-INF/tiles/account/newaccountscript.jsp"></put-attribute>
		<put-attribute name="title" value="Create Account"></put-attribute>
		<put-attribute name="content" value="/WEB-INF/tiles/account/newaccount.jsp"></put-attribute>
	</definition>
	
	<definition name="accountcreated" extends="parking.base">
		<put-attribute name="title" value="Account Created Page"></put-attribute>
		<put-attribute name="content" value="/WEB-INF/tiles/account/accountcreated.jsp"></put-attribute>
	</definition>
	
	<definition name="userdetails" extends="parking.base">
		<put-attribute name="title" value="Dane szczegolowe uzytkownika"></put-attribute>
		<put-attribute name="content" value="/WEB-INF/tiles/account/userdetails.jsp"></put-attribute>
	</definition>
	
	<definition name="userdetailsupdated" extends="parking.base">
		<put-attribute name="title" value="Dane zaktualizowane"></put-attribute>
		<put-attribute name="content" value="/WEB-INF/tiles/account/userdetailsupdated.jsp"></put-attribute>
	</definition>
	
	<definition name="changepw" extends="parking.base">
		<put-attribute name="title" value="Zmien swoje haslo"></put-attribute>
		<put-attribute name="content" value="/WEB-INF/tiles/account/changepw.jsp"></put-attribute>
	</definition>
	
	<definition name="pwupdated" extends="parking.base">
		<put-attribute name="title" value="Haslo zostalo zmienione"></put-attribute>
		<put-attribute name="content" value="/WEB-INF/tiles/account/pwupdated.jsp"></put-attribute>
	</definition>
	
	<definition name="admin" extends="parking.base">
		<put-attribute name="title" value="Admin Page"></put-attribute>
		<put-attribute name="content" value="/WEB-INF/tiles/admin.jsp"></put-attribute>
	</definition>
	
	<definition name="denied" extends="parking.base">
		<put-attribute name="title" value="Access Denied Page"></put-attribute>
		<put-attribute name="content" value="/WEB-INF/tiles/other/denied.jsp"></put-attribute>
	</definition>
	
	<definition name="error" extends="parking.base">
		<put-attribute name="title" value="Something goes wrong"></put-attribute>
		<put-attribute name="content" value="/WEB-INF/tiles/other/error.jsp"></put-attribute>
	</definition>
	
	<definition name="cennik" extends="parking.base">
		<put-attribute name="title" value="Cennik parkingu"></put-attribute>
		<put-attribute name="content" value="/WEB-INF/tiles/cennik/cennik.jsp"></put-attribute>
	</definition>
	
	<definition name="editcennik" extends="parking.base">
		<put-attribute name="title" value="Zmien cennik parkingu"></put-attribute>
		<put-attribute name="content" value="/WEB-INF/tiles/cennik/editcennik.jsp"></put-attribute>
	</definition>
	
	<definition name="addtocennik" extends="parking.base">
		<put-attribute name="title" value="Dodaj pozycje do cennika"></put-attribute>
		<put-attribute name="content" value="/WEB-INF/tiles/cennik/addtocennik.jsp"></put-attribute>
	</definition>
	
	<definition name="cennikupdated" extends="parking.base">
		<put-attribute name="title" value="Cennik zostal zaktualizowany"></put-attribute>
		<put-attribute name="content" value="/WEB-INF/tiles/cennik/cennikupdated.jsp"></put-attribute>
	</definition>
	
	<definition name="kontakt" extends="parking.base">
		<put-attribute name="title" value="Skontaktuj sie z nami"></put-attribute>
		<put-attribute name="content" value="/WEB-INF/tiles/kontakt.jsp"></put-attribute>
	</definition>
	
	<definition name="parkingspaces" extends="parking.base">
		<put-attribute name="title" value="Dostepne miejsca parkingowe"></put-attribute>
		<put-attribute name="content" value="/WEB-INF/tiles/reservation/parkingspaces.jsp"></put-attribute>
	</definition>
	
	<definition name="editparkingspaces" extends="parking.base">
		<put-attribute name="title" value="Edytuj dostepne miejsca parkingowe"></put-attribute>
		<put-attribute name="content" value="/WEB-INF/tiles/reservation/editparkingspaces.jsp"></put-attribute>
	</definition>
	
	<definition name="newparkingspace" extends="parking.base">
		<put-attribute name="title" value="Stworz miejsce parkingowe"></put-attribute>
		<put-attribute name="content" value="/WEB-INF/tiles/reservation/newparkingspace.jsp"></put-attribute>
	</definition>
	
	<definition name="parkingupdated" extends="parking.base">
		<put-attribute name="title" value="Parking zostal zaktualizowany"></put-attribute>
		<put-attribute name="content" value="/WEB-INF/tiles/reservation/parkingupdated.jsp"></put-attribute>
	</definition>
	
	<definition name="newreservation" extends="parking.base">
		<put-attribute name="title" value="Dokonaj rezerwacji"></put-attribute>
		<put-attribute name="content" value="/WEB-INF/tiles/reservation/newreservation.jsp"></put-attribute>
	</definition>
	
	<definition name="reservationcreated" extends="parking.base">
		<put-attribute name="title" value="Dokonano rezerwacji"></put-attribute>
		<put-attribute name="content" value="/WEB-INF/tiles/reservation/reservationcreated.jsp"></put-attribute>
	</definition>
	
	<definition name="nospaces" extends="parking.base">
		<put-attribute name="title" value="Brak dostepnych miejsc parkingowych"></put-attribute>
		<put-attribute name="content" value="/WEB-INF/tiles/reservation/nospaces.jsp"></put-attribute>
	</definition>
	
	<definition name="myreservations" extends="parking.base">
		<put-attribute name="title" value="Moje rezerwacje"></put-attribute>
		<put-attribute name="content" value="/WEB-INF/tiles/reservation/myreservations.jsp"></put-attribute>
	</definition>
	
</tiles-definitions>